plain/code/CHANGELOG.md
plain/code/README.md
plain/code/__init__.py
plain/code/annotations.py
plain/code/biome.py
plain/code/biome_defaults.json
plain/code/cli.py
plain/code/entrypoints.py
plain/code/ruff_defaults.toml
plain/code/skills/plain-fix/SKILL.md
plain_code-0.20.0.dist-info/METADATA
plain_code-0.20.0.dist-info/WHEEL
plain_code-0.20.0.dist-info/entry_points.txt
plain_code-0.20.0.dist-info/licenses/LICENSE
plain_code-0.20.0.dist-info/RECORD
